yostlabs/__init__.py
yostlabs/communication/__init__.py
yostlabs/communication/base.py
yostlabs/communication/ble.py
yostlabs/communication/serial.py
yostlabs/math/__init__.py
yostlabs/math/quaternion.py
yostlabs/math/vector.py
yostlabs/tss3/__init__.py
yostlabs/tss3/api.py
yostlabs/tss3/consts.py
yostlabs/tss3/eepts.py
yostlabs/tss3/utils/__init__.py
yostlabs/tss3/utils/calibration.py
yostlabs/tss3/utils/parser.py
yostlabs/tss3/utils/streaming.py
yostlabs/tss3/utils/version.py
yostlabs-2025.10.24.dist-info/METADATA
yostlabs-2025.10.24.dist-info/WHEEL
yostlabs-2025.10.24.dist-info/licenses/LICENSE
yostlabs-2025.10.24.dist-info/RECORD
